walrus/__init__.py
walrus/client.py
walrus_python-0.1.0.dist-info/licenses/LICENSE.md
walrus_python-0.1.0.dist-info/METADATA
walrus_python-0.1.0.dist-info/WHEEL
walrus_python-0.1.0.dist-info/top_level.txt
walrus_python-0.1.0.dist-info/RECORD
