Metadata-Version: 2.4
Name: walrus-python
Version: 0.1.0
Summary: Python SDK for Walrus, a decentralized blob storage protocol
Author-email: Kevin Ayling <kevin@standardcryptovc.com>
License: MIT
Requires-Python: >=3.8
License-File: LICENSE.md
Requires-Dist: requests>=2.0.0
Dynamic: license-file
